AUTHORS
COPYING
LICENSE
MANIFEST.in
README
setup.py
docs/Makefile
docs/make.bat
docs/source/conf.py
docs/source/global.rst.inc
docs/source/index.rst
docs/source/_themes/sphinx-theme-minimalism/.git
docs/source/_themes/sphinx-theme-minimalism/.gitignore
docs/source/_themes/sphinx-theme-minimalism/README
docs/source/_themes/sphinx-theme-minimalism/layout.html
docs/source/_themes/sphinx-theme-minimalism/relations.html
docs/source/_themes/sphinx-theme-minimalism/theme.conf
docs/source/_themes/sphinx-theme-minimalism/theme_style.py
docs/source/_themes/sphinx-theme-minimalism/static/minimalism.css_t
docs/source/_themes/sphinx-theme-minimalism/static/pocoo.png
docs/source/api/codec.rst
docs/source/api/general.rst
docs/source/api/net.rst
docs/source/api/os.rst
docs/source/api/security.rst
docs/source/guides/hacking.rst
mom/__init__.py
mom/_alt_builtins.py
mom/_compat.py
mom/_gmpy_math.py
mom/_prime_sieve.py
mom/builtins.py
mom/collections.py
mom/decorators.py
mom/functional.py
mom/gmp.py
mom/itertools.py
mom/math.py
mom/mimeparse.py
mom/prime_sieve.py
mom/string.py
mom/tracer.py
mom.egg-info/PKG-INFO
mom.egg-info/SOURCES.txt
mom.egg-info/dependency_links.txt
mom.egg-info/requires.txt
mom.egg-info/top_level.txt
mom.egg-info/zip-safe
mom/_types/__init__.py
mom/_types/bytearray.py
mom/codec/__init__.py
mom/codec/_alt_base.py
mom/codec/_alt_integer.py
mom/codec/_base.py
mom/codec/_json_compat.py
mom/codec/base36.py
mom/codec/base58.py
mom/codec/base62.py
mom/codec/base85.py
mom/codec/integer.py
mom/codec/json.py
mom/codec/text.py
mom/net/__init__.py
mom/net/data_uri.py
mom/os/__init__.py
mom/os/path.py
mom/os/patterns.py
mom/security/__init__.py
mom/security/hash.py
mom/security/random.py
mom/security/codec/__init__.py
mom/security/codec/asn1/__init__.py
mom/security/codec/asn1/rsadsa.py
mom/security/codec/asn1/x509.py
mom/security/codec/pem/__init__.py
mom/security/codec/pem/rsa.py
mom/security/codec/pem/x509.py
mom/security/rsa/__init__.py
mom/security/rsa/keys.py
mom/security/rsa/pycrypto.py