Metadata-Version: 1.1
Name: mom
Version: 0.1.3
Summary: Python utility library.
Home-page: http://github.com/gorakhargosh/mom
Author: Yesudeep Mangalapilly
Author-email: yesudeep@google.com
License: Apache Software License 2.0
Keywords: python utilities
Platform: any
Classifier: Development Status :: 4 - Beta
Classifier: Intended Audience :: Developers
Classifier: License :: OSI Approved :: Apache Software License
Classifier: Operating System :: OS Independent
Classifier: Programming Language :: Python
Classifier: Topic :: Software Development :: Libraries :: Python Modules
